{
    "meta": {
        "tried": 999,
        "allowed": 952,
        "blocked": 47,
        "errors": 0
    },
    "domains": {
        "preventdivorcect.com": {
            "ttl": 101,
            "ipid": 21588,
            "responses": 1
        },
        "brinquedobom.com": {
            "ttl": 101,
            "ipid": 21588,
            "responses": 1
        },
        "53turizm.com": {
            "ttl": 101,
            "ipid": 21588,
            "responses": 2
        },
        "clubfivemx.com": {
            "ttl": 101,
            "ipid": 21588,
            "responses": 2
        },
        "notchilla.com": {
            "ttl": 101,
            "ipid": 21588,
            "responses": 1
        },
        "ahmadrazaghi.com": {
            "ttl": 101,
            "ipid": 21588,
            "responses": 1
        },
        "sunshinecoasttrail.com": {
            "ttl": 101,
            "ipid": 21588,
            "responses": 3
        },
        "lmttechnologies.com": {
            "ttl": 101,
            "ipid": 21588,
            "responses": 3
        },
        "robertkandell.com": {
            "ttl": 101,
            "ipid": 21588,
            "responses": 1
        },
        "ifounddeals.com": {
            "ttl": 101,
            "ipid": 21588,
            "responses": 1
        },
        "theamericanpeopleknow.com": {
            "ttl": 101,
            "ipid": 21588,
            "responses": 3
        },
        "highclimbsolutions.com": {
            "ttl": 101,
            "ipid": 21588,
            "responses": 5
        },
        "levgodt.com": {
            "ttl": 101,
            "ipid": 21588,
            "responses": 3
        },
        "filteringtheworld.com": {
            "ttl": 101,
            "ipid": 21588,
            "responses": 2
        },
        "meksnme.com": {
            "ttl": 101,
            "ipid": 21588,
            "responses": 5
        },
        "lingjiapu.com": {
            "ttl": 101,
            "ipid": 21588,
            "responses": 1
        },
        "j-mconstruction.com": {
            "ttl": 101,
            "ipid": 21588,
            "responses": 1
        },
        "pouzadoux.com": {
            "ttl": 101,
            "ipid": 21588,
            "responses": 4
        },
        "krauserdentalimplants.com": {
            "ttl": 101,
            "ipid": 21588,
            "responses": 2
        },
        "groveatsaintandrews.com": {
            "ttl": 101,
            "ipid": 21588,
            "responses": 1
        },
        "bellezaencanto.com": {
            "ttl": 101,
            "ipid": 21588,
            "responses": 1
        },
        "020amsterdam.com": {
            "ttl": 101,
            "ipid": 21588,
            "responses": 1
        },
        "otimizaconstrucoes.com": {
            "ttl": 101,
            "ipid": 21588,
            "responses": 1
        },
        "comeingetoff.com": {
            "ttl": 101,
            "ipid": 21588,
            "responses": 1
        },
        "559311.com": {
            "ttl": 101,
            "ipid": 21588,
            "responses": 2
        },
        "tritonsha.com": {
            "ttl": 101,
            "ipid": 21588,
            "responses": 1
        },
        "goujiapu.com": {
            "ttl": 101,
            "ipid": 21588,
            "responses": 1
        },
        "crosbyrdconstruction.com": {
            "ttl": 101,
            "ipid": 21588,
            "responses": 3
        },
        "propertydatabaseservice.com": {
            "ttl": 101,
            "ipid": 21588,
            "responses": 2
        },
        "zuidport.com": {
            "ttl": 101,
            "ipid": 21588,
            "responses": 1
        },
        "investment-hr.com": {
            "ttl": 101,
            "ipid": 21588,
            "responses": 2
        },
        "sluvoo.com": {
            "ttl": 101,
            "ipid": 21588,
            "responses": 5
        },
        "formulaappraisal.com": {
            "ttl": 101,
            "ipid": 21588,
            "responses": 2
        },
        "caninerewind.com": {
            "ttl": 101,
            "ipid": 21588,
            "responses": 1
        },
        "keyslockspadlocks.com": {
            "ttl": 101,
            "ipid": 21588,
            "responses": 3
        },
        "rustikraft.com": {
            "ttl": 101,
            "ipid": 21588,
            "responses": 7
        },
        "addthishotel.com": {
            "ttl": 101,
            "ipid": 21588,
            "responses": 2
        },
        "gsdeck.com": {
            "ttl": 101,
            "ipid": 21588,
            "responses": 2
        },
        "heliothefilm.com": {
            "ttl": 101,
            "ipid": 21588,
            "responses": 3
        },
        "samuibrand.com": {
            "ttl": 101,
            "ipid": 21588,
            "responses": 3
        },
        "helegance.com": {
            "ttl": 101,
            "ipid": 21588,
            "responses": 5
        },
        "brightnowsigns.com": {
            "ttl": 101,
            "ipid": 21588,
            "responses": 1
        },
        "volvopentadealerdirectory.com": {
            "ttl": 101,
            "ipid": 21588,
            "responses": 6
        },
        "nnnbet365.com": {
            "ttl": 101,
            "ipid": 21588,
            "responses": 4
        },
        "besttripdestinations.com": {
            "ttl": 101,
            "ipid": 21588,
            "responses": 1
        },
        "slaintebeer.com": {
            "ttl": 101,
            "ipid": 21588,
            "responses": 5
        },
        "medicalhealthcaresite.com": {
            "ttl": 101,
            "ipid": 21588,
            "responses": 1
        }
    }
}