{
    "meta": {
        "tried": 999,
        "allowed": 917,
        "blocked": 82,
        "errors": 0
    },
    "domains": {
        "naplespapers.com": {
            "ttl": 101,
            "ipid": 21588,
            "responses": 1
        },
        "lasvegasewaste.com": {
            "ttl": 101,
            "ipid": 21588,
            "responses": 4
        },
        "sodaoutfitters.com": {
            "ttl": 101,
            "ipid": 21588,
            "responses": 2
        },
        "grmedspa.com": {
            "ttl": 101,
            "ipid": 21588,
            "responses": 7
        },
        "newyorkcitycourtreporter.com": {
            "ttl": 101,
            "ipid": 21588,
            "responses": 4
        },
        "davidsethcohen.com": {
            "ttl": 101,
            "ipid": 21588,
            "responses": 4
        },
        "lawtechdogs.com": {
            "ttl": 101,
            "ipid": 21588,
            "responses": 11
        },
        "lucasoilproductnews.com": {
            "ttl": 101,
            "ipid": 21588,
            "responses": 3
        },
        "hotrodproductnews.com": {
            "ttl": 101,
            "ipid": 21588,
            "responses": 3
        },
        "dezotrading.com": {
            "ttl": 101,
            "ipid": 21588,
            "responses": 3
        },
        "flowmasterproductnews.com": {
            "ttl": 101,
            "ipid": 21588,
            "responses": 9
        },
        "jr-leasing.com": {
            "ttl": 101,
            "ipid": 21588,
            "responses": 4
        },
        "mattfax.com": {
            "ttl": 101,
            "ipid": 21588,
            "responses": 2
        },
        "rahulkevintanna.com": {
            "ttl": 101,
            "ipid": 21588,
            "responses": 7
        },
        "skimayrhofen.com": {
            "ttl": 101,
            "ipid": 21588,
            "responses": 6
        },
        "bossshepherdsdc.com": {
            "ttl": 101,
            "ipid": 21588,
            "responses": 2
        },
        "demirorenoto.com": {
            "ttl": 101,
            "ipid": 21588,
            "responses": 3
        },
        "paizhuan.com": {
            "ttl": 101,
            "ipid": 21588,
            "responses": 2
        },
        "citycyclingchampionships.com": {
            "ttl": 101,
            "ipid": 21588,
            "responses": 1
        },
        "lisamv.com": {
            "ttl": 101,
            "ipid": 21588,
            "responses": 4
        },
        "museumofgoodtaste.com": {
            "ttl": 101,
            "ipid": 21588,
            "responses": 1
        },
        "confickerworkinggroup.com": {
            "ttl": 101,
            "ipid": 21588,
            "responses": 3
        },
        "oilchangedealspro.com": {
            "ttl": 101,
            "ipid": 21588,
            "responses": 2
        },
        "suituptuxedoelp.com": {
            "ttl": 101,
            "ipid": 21588,
            "responses": 12
        },
        "find-cheapest-auto-insurance.com": {
            "ttl": 101,
            "ipid": 21588,
            "responses": 2
        },
        "3526831512.com": {
            "ttl": 101,
            "ipid": 21588,
            "responses": 7
        },
        "soloimagenescool.com": {
            "ttl": 101,
            "ipid": 21588,
            "responses": 6
        },
        "keystonebahamas.com": {
            "ttl": 101,
            "ipid": 21588,
            "responses": 1
        },
        "drendakeesee.com": {
            "ttl": 101,
            "ipid": 21588,
            "responses": 4
        },
        "getlosgatosrealestate.com": {
            "ttl": 101,
            "ipid": 21588,
            "responses": 3
        },
        "belladelux.com": {
            "ttl": 101,
            "ipid": 21588,
            "responses": 4
        },
        "paintballunquera.com": {
            "ttl": 101,
            "ipid": 21588,
            "responses": 7
        },
        "johnwilcoxfertility.com": {
            "ttl": 101,
            "ipid": 21588,
            "responses": 2
        },
        "won4allall4won.com": {
            "ttl": 101,
            "ipid": 21588,
            "responses": 1
        },
        "100mostexpensive.com": {
            "ttl": 101,
            "ipid": 21588,
            "responses": 1
        },
        "embarrassables.com": {
            "ttl": 101,
            "ipid": 21588,
            "responses": 5
        },
        "brooklynseltzer.com": {
            "ttl": 101,
            "ipid": 21588,
            "responses": 3
        },
        "antalgl.com": {
            "ttl": 101,
            "ipid": 21588,
            "responses": 4
        },
        "vodafonepass.com": {
            "ttl": 101,
            "ipid": 21588,
            "responses": 2
        },
        "syxxr.com": {
            "ttl": 101,
            "ipid": 21588,
            "responses": 5
        },
        "33brickstreet.com": {
            "ttl": 101,
            "ipid": 21588,
            "responses": 6
        },
        "cpahn.com": {
            "ttl": 101,
            "ipid": 21588,
            "responses": 3
        },
        "amperimagesciences.com": {
            "ttl": 101,
            "ipid": 21588,
            "responses": 5
        },
        "hg79904.com": {
            "ttl": 101,
            "ipid": 21588,
            "responses": 4
        },
        "justhelpyou.com": {
            "ttl": 101,
            "ipid": 21588,
            "responses": 2
        },
        "windowtintingaustin.com": {
            "ttl": 101,
            "ipid": 21588,
            "responses": 4
        },
        "tvshows-addicts.com": {
            "ttl": 101,
            "ipid": 21588,
            "responses": 2
        },
        "ryanjchampagne.com": {
            "ttl": 101,
            "ipid": 21588,
            "responses": 6
        },
        "plugintonature.com": {
            "ttl": 101,
            "ipid": 21588,
            "responses": 6
        },
        "cacactusbrandy.com": {
            "ttl": 101,
            "ipid": 21588,
            "responses": 2
        },
        "3craft.com": {
            "ttl": 101,
            "ipid": 21588,
            "responses": 9
        },
        "logis-de-france-loiret.com": {
            "ttl": 101,
            "ipid": 21588,
            "responses": 4
        },
        "mygallapp.com": {
            "ttl": 101,
            "ipid": 21588,
            "responses": 5
        },
        "nowoczesnewnetrza.com": {
            "ttl": 101,
            "ipid": 21588,
            "responses": 1
        },
        "klandr.com": {
            "ttl": 101,
            "ipid": 21588,
            "responses": 1
        },
        "irvineharmonica.com": {
            "ttl": 101,
            "ipid": 21588,
            "responses": 9
        },
        "yudaca.com": {
            "ttl": 101,
            "ipid": 21588,
            "responses": 3
        },
        "montgomerycountywindowcleaning.com": {
            "ttl": 101,
            "ipid": 21588,
            "responses": 2
        },
        "chrisslavinskas.com": {
            "ttl": 101,
            "ipid": 21588,
            "responses": 6
        },
        "cathercist.com": {
            "ttl": 101,
            "ipid": 21588,
            "responses": 8
        },
        "pattygreenwrites.com": {
            "ttl": 101,
            "ipid": 21588,
            "responses": 3
        },
        "bmxfu.com": {
            "ttl": 101,
            "ipid": 21588,
            "responses": 3
        },
        "54321e.com": {
            "ttl": 101,
            "ipid": 21588,
            "responses": 4
        },
        "andrewnadeau.com": {
            "ttl": 101,
            "ipid": 21588,
            "responses": 2
        },
        "southerncalifornianative.com": {
            "ttl": 101,
            "ipid": 21588,
            "responses": 4
        },
        "sixdegreesicons.com": {
            "ttl": 97,
            "ipid": 40511,
            "responses": 2
        },
        "lovesartandsculpture.com": {
            "ttl": 101,
            "ipid": 21588,
            "responses": 5
        },
        "getpascorealestate.com": {
            "ttl": 101,
            "ipid": 21588,
            "responses": 2
        },
        "v13608.com": {
            "ttl": 101,
            "ipid": 21588,
            "responses": 2
        },
        "accsell.com": {
            "ttl": 101,
            "ipid": 21588,
            "responses": 4
        },
        "rs4doorsandgates.com": {
            "ttl": 101,
            "ipid": 21588,
            "responses": 4
        },
        "miformamemoryfoammattress.com": {
            "ttl": 101,
            "ipid": 21588,
            "responses": 2
        },
        "agungo.com": {
            "ttl": 101,
            "ipid": 21588,
            "responses": 2
        },
        "thepaperworkstore.com": {
            "ttl": 101,
            "ipid": 21588,
            "responses": 4
        },
        "acurareleases.com": {
            "ttl": 101,
            "ipid": 21588,
            "responses": 4
        },
        "technicalreleases.com": {
            "ttl": 101,
            "ipid": 21588,
            "responses": 4
        },
        "cityoftempleterrace.com": {
            "ttl": 101,
            "ipid": 21588,
            "responses": 2
        },
        "financialrepairkit.com": {
            "ttl": 101,
            "ipid": 21588,
            "responses": 5
        },
        "chaparralwebconcepts.com": {
            "ttl": 101,
            "ipid": 21588,
            "responses": 5
        },
        "poltergeistsandparamours.com": {
            "ttl": 101,
            "ipid": 21588,
            "responses": 3
        },
        "shortips.com": {
            "ttl": 101,
            "ipid": 21588,
            "responses": 2
        },
        "lupolover-tcpa-violator.com": {
            "ttl": 101,
            "ipid": 21588,
            "responses": 3
        }
    }
}