{
    "meta": {
        "tried": 999,
        "allowed": 901,
        "blocked": 98,
        "errors": 0
    },
    "domains": {
        "w4c8ex.info": {
            "ttl": 101,
            "ipid": 21588,
            "responses": 2
        },
        "w4cyla.info": {
            "ttl": 101,
            "ipid": 21588,
            "responses": 4
        },
        "w4e8i.info": {
            "ttl": 101,
            "ipid": 21588,
            "responses": 6
        },
        "w4h4.info": {
            "ttl": 101,
            "ipid": 21588,
            "responses": 1
        },
        "w4j8.info": {
            "ttl": 101,
            "ipid": 21588,
            "responses": 11
        },
        "w4jbr7.info": {
            "ttl": 101,
            "ipid": 21588,
            "responses": 1
        },
        "w4kokh.info": {
            "ttl": 101,
            "ipid": 21588,
            "responses": 6
        },
        "w4ll3t.info": {
            "ttl": 101,
            "ipid": 21588,
            "responses": 3
        },
        "w4p2.info": {
            "ttl": 101,
            "ipid": 21588,
            "responses": 6
        },
        "w4snz.info": {
            "ttl": 101,
            "ipid": 21588,
            "responses": 4
        },
        "w4t.info": {
            "ttl": 101,
            "ipid": 21588,
            "responses": 2
        },
        "w4wn.info": {
            "ttl": 101,
            "ipid": 21588,
            "responses": 5
        },
        "w4wu0k.info": {
            "ttl": 101,
            "ipid": 21588,
            "responses": 3
        },
        "w514az.info": {
            "ttl": 101,
            "ipid": 21588,
            "responses": 4
        },
        "w5239b.info": {
            "ttl": 101,
            "ipid": 21588,
            "responses": 5
        },
        "w5303.info": {
            "ttl": 101,
            "ipid": 21588,
            "responses": 7
        },
        "w5367s.info": {
            "ttl": 101,
            "ipid": 21588,
            "responses": 2
        },
        "w54mvj.info": {
            "ttl": 101,
            "ipid": 21588,
            "responses": 4
        },
        "w55.info": {
            "ttl": 101,
            "ipid": 21588,
            "responses": 6
        },
        "w5528f.info": {
            "ttl": 101,
            "ipid": 21588,
            "responses": 6
        },
        "w55v883.info": {
            "ttl": 101,
            "ipid": 21588,
            "responses": 5
        },
        "w56.info": {
            "ttl": 101,
            "ipid": 21588,
            "responses": 1
        },
        "w5663q.info": {
            "ttl": 101,
            "ipid": 21588,
            "responses": 4
        },
        "w5681g.info": {
            "ttl": 101,
            "ipid": 21588,
            "responses": 8
        },
        "w5684canary.info": {
            "ttl": 101,
            "ipid": 21588,
            "responses": 3
        },
        "w5938.info": {
            "ttl": 101,
            "ipid": 21588,
            "responses": 1
        },
        "w5997r.info": {
            "ttl": 101,
            "ipid": 21588,
            "responses": 9
        },
        "w5f.info": {
            "ttl": 101,
            "ipid": 21588,
            "responses": 6
        },
        "w5i5xi.info": {
            "ttl": 101,
            "ipid": 21588,
            "responses": 4
        },
        "w5jcg.info": {
            "ttl": 101,
            "ipid": 21588,
            "responses": 5
        },
        "w5lvc.info": {
            "ttl": 101,
            "ipid": 21588,
            "responses": 4
        },
        "w5m11d.info": {
            "ttl": 101,
            "ipid": 21588,
            "responses": 6
        },
        "w5nx1b.info": {
            "ttl": 101,
            "ipid": 21588,
            "responses": 3
        },
        "w5s7.info": {
            "ttl": 101,
            "ipid": 21588,
            "responses": 7
        },
        "w5yg5b2.info": {
            "ttl": 101,
            "ipid": 21588,
            "responses": 6
        },
        "w6357m.info": {
            "ttl": 101,
            "ipid": 21588,
            "responses": 1
        },
        "w63h51.info": {
            "ttl": 101,
            "ipid": 21588,
            "responses": 4
        },
        "w63rq8.info": {
            "ttl": 101,
            "ipid": 21588,
            "responses": 5
        },
        "w6517d.info": {
            "ttl": 101,
            "ipid": 21588,
            "responses": 3
        },
        "w6620.info": {
            "ttl": 101,
            "ipid": 21588,
            "responses": 4
        },
        "w69g97.info": {
            "ttl": 101,
            "ipid": 21588,
            "responses": 7
        },
        "w6b1aj.info": {
            "ttl": 101,
            "ipid": 21588,
            "responses": 4
        },
        "w6b4p.info": {
            "ttl": 101,
            "ipid": 21588,
            "responses": 4
        },
        "w6bgxp.info": {
            "ttl": 101,
            "ipid": 21588,
            "responses": 7
        },
        "w6k8.info": {
            "ttl": 101,
            "ipid": 21588,
            "responses": 12
        },
        "w6o.info": {
            "ttl": 101,
            "ipid": 21588,
            "responses": 8
        },
        "w6ol0d.info": {
            "ttl": 101,
            "ipid": 21588,
            "responses": 3
        },
        "w6si3l.info": {
            "ttl": 101,
            "ipid": 21588,
            "responses": 6
        },
        "w6vtwu.info": {
            "ttl": 101,
            "ipid": 21588,
            "responses": 6
        },
        "w6wt7u.info": {
            "ttl": 101,
            "ipid": 21588,
            "responses": 4
        },
        "w6ytp8.info": {
            "ttl": 101,
            "ipid": 21588,
            "responses": 5
        },
        "w70.info": {
            "ttl": 101,
            "ipid": 21588,
            "responses": 3
        },
        "w7125z.info": {
            "ttl": 101,
            "ipid": 21588,
            "responses": 4
        },
        "w7187f.info": {
            "ttl": 101,
            "ipid": 21588,
            "responses": 5
        },
        "w737z8.info": {
            "ttl": 101,
            "ipid": 21588,
            "responses": 2
        },
        "w7568i.info": {
            "ttl": 101,
            "ipid": 21588,
            "responses": 6
        },
        "w77.info": {
            "ttl": 101,
            "ipid": 21588,
            "responses": 5
        },
        "w7785l.info": {
            "ttl": 101,
            "ipid": 21588,
            "responses": 4
        },
        "w780.info": {
            "ttl": 101,
            "ipid": 21588,
            "responses": 3
        },
        "w783.info": {
            "ttl": 101,
            "ipid": 21588,
            "responses": 1
        },
        "w7857e.info": {
            "ttl": 101,
            "ipid": 21588,
            "responses": 5
        },
        "w7c0dp.info": {
            "ttl": 101,
            "ipid": 21588,
            "responses": 8
        },
        "w7e5txg.info": {
            "ttl": 101,
            "ipid": 21588,
            "responses": 7
        },
        "w7epcd9aduq2ad9rn.info": {
            "ttl": 101,
            "ipid": 21588,
            "responses": 2
        },
        "w7etfbatukauihtf.info": {
            "ttl": 101,
            "ipid": 21588,
            "responses": 4
        },
        "w7h.info": {
            "ttl": 101,
            "ipid": 21588,
            "responses": 4
        },
        "w7h8.info": {
            "ttl": 101,
            "ipid": 21588,
            "responses": 7
        },
        "w7o.info": {
            "ttl": 101,
            "ipid": 21588,
            "responses": 1
        },
        "w7r1.info": {
            "ttl": 101,
            "ipid": 21588,
            "responses": 1
        },
        "w7tij4.info": {
            "ttl": 101,
            "ipid": 21588,
            "responses": 3
        },
        "w7tuim.info": {
            "ttl": 101,
            "ipid": 21588,
            "responses": 7
        },
        "w7unpr.info": {
            "ttl": 101,
            "ipid": 21588,
            "responses": 5
        },
        "w7v9trc.info": {
            "ttl": 101,
            "ipid": 21588,
            "responses": 11
        },
        "w7wz9.info": {
            "ttl": 101,
            "ipid": 21588,
            "responses": 5
        },
        "w7zjaa.info": {
            "ttl": 101,
            "ipid": 21588,
            "responses": 2
        },
        "w8005a.info": {
            "ttl": 101,
            "ipid": 21588,
            "responses": 2
        },
        "w82gg.info": {
            "ttl": 101,
            "ipid": 21588,
            "responses": 7
        },
        "w831791.info": {
            "ttl": 101,
            "ipid": 21588,
            "responses": 6
        },
        "w84dchance2bhealthy.info": {
            "ttl": 101,
            "ipid": 21588,
            "responses": 4
        },
        "w8598b.info": {
            "ttl": 101,
            "ipid": 21588,
            "responses": 2
        },
        "w8683b.info": {
            "ttl": 97,
            "ipid": 63332,
            "responses": 2
        },
        "w8789t.info": {
            "ttl": 101,
            "ipid": 21588,
            "responses": 5
        },
        "w88198.info": {
            "ttl": 101,
            "ipid": 21588,
            "responses": 8
        },
        "w8877.info": {
            "ttl": 101,
            "ipid": 21588,
            "responses": 4
        },
        "w88club.info": {
            "ttl": 101,
            "ipid": 21588,
            "responses": 5
        },
        "w88coy.info": {
            "ttl": 101,
            "ipid": 21588,
            "responses": 6
        },
        "w88he.info": {
            "ttl": 101,
            "ipid": 21588,
            "responses": 10
        },
        "w88info.info": {
            "ttl": 101,
            "ipid": 21588,
            "responses": 6
        },
        "w88love.info": {
            "ttl": 101,
            "ipid": 21588,
            "responses": 3
        },
        "w88thailander.info": {
            "ttl": 101,
            "ipid": 21588,
            "responses": 7
        },
        "w88tian.info": {
            "ttl": 100,
            "ipid": 6502,
            "responses": 2
        },
        "w88w.info": {
            "ttl": 101,
            "ipid": 21588,
            "responses": 5
        },
        "w88w181.info": {
            "ttl": 101,
            "ipid": 21588,
            "responses": 6
        },
        "w88xiao.info": {
            "ttl": 58,
            "ipid": 13315,
            "responses": 2
        },
        "w8g.info": {
            "ttl": 101,
            "ipid": 21588,
            "responses": 4
        },
        "w8lza.info": {
            "ttl": 101,
            "ipid": 21588,
            "responses": 5
        },
        "w8p.info": {
            "ttl": 100,
            "ipid": 56674,
            "responses": 2
        },
        "w8q3.info": {
            "ttl": 101,
            "ipid": 21588,
            "responses": 2
        }
    }
}