{
    "meta": {
        "tried": 999,
        "allowed": 924,
        "blocked": 75,
        "errors": 0
    },
    "domains": {
        "flyingkipper.net": {
            "ttl": 101,
            "ipid": 21588,
            "responses": 2
        },
        "arcobalocco.net": {
            "ttl": 101,
            "ipid": 21588,
            "responses": 3
        },
        "godaddyweb.net": {
            "ttl": 101,
            "ipid": 21588,
            "responses": 2
        },
        "freespiritsingles.net": {
            "ttl": 101,
            "ipid": 21588,
            "responses": 3
        },
        "xetrungquoc.net": {
            "ttl": 101,
            "ipid": 21588,
            "responses": 4
        },
        "stregisgetaways.net": {
            "ttl": 101,
            "ipid": 21588,
            "responses": 4
        },
        "lavolieredesdebutants.net": {
            "ttl": 101,
            "ipid": 21588,
            "responses": 3
        },
        "sandhlllspublishing.net": {
            "ttl": 101,
            "ipid": 21588,
            "responses": 5
        },
        "silixa.net": {
            "ttl": 101,
            "ipid": 21588,
            "responses": 4
        },
        "romanceinitiative.net": {
            "ttl": 101,
            "ipid": 21588,
            "responses": 5
        },
        "thedentalbusiness.net": {
            "ttl": 101,
            "ipid": 21588,
            "responses": 3
        },
        "orange-spot.net": {
            "ttl": 101,
            "ipid": 21588,
            "responses": 2
        },
        "balneariourbano.net": {
            "ttl": 101,
            "ipid": 21588,
            "responses": 3
        },
        "elisapansini.net": {
            "ttl": 101,
            "ipid": 21588,
            "responses": 1
        },
        "coopforseniorcare.net": {
            "ttl": 101,
            "ipid": 21588,
            "responses": 3
        },
        "bitwash.net": {
            "ttl": 101,
            "ipid": 21588,
            "responses": 1
        },
        "congdong365bong.net": {
            "ttl": 101,
            "ipid": 21588,
            "responses": 4
        },
        "52jiaocheng.net": {
            "ttl": 101,
            "ipid": 21588,
            "responses": 3
        },
        "thecymbalroom.net": {
            "ttl": 101,
            "ipid": 21588,
            "responses": 4
        },
        "fbcfm.net": {
            "ttl": 101,
            "ipid": 21588,
            "responses": 1
        },
        "bain-marie-culinaria.net": {
            "ttl": 101,
            "ipid": 21588,
            "responses": 2
        },
        "fh58.net": {
            "ttl": 101,
            "ipid": 21588,
            "responses": 2
        },
        "aogguild.net": {
            "ttl": 101,
            "ipid": 21588,
            "responses": 3
        },
        "francisschaeffer.net": {
            "ttl": 101,
            "ipid": 21588,
            "responses": 5
        },
        "posterbase.net": {
            "ttl": 101,
            "ipid": 21588,
            "responses": 1
        },
        "accessck.net": {
            "ttl": 101,
            "ipid": 21588,
            "responses": 8
        },
        "vayacampingclub.net": {
            "ttl": 101,
            "ipid": 21588,
            "responses": 1
        },
        "tcirrigation.net": {
            "ttl": 101,
            "ipid": 21588,
            "responses": 1
        },
        "zeroideas.net": {
            "ttl": 101,
            "ipid": 21588,
            "responses": 2
        },
        "ada-podcast.net": {
            "ttl": 101,
            "ipid": 21588,
            "responses": 3
        },
        "downroundtheaugi.net": {
            "ttl": 101,
            "ipid": 21588,
            "responses": 2
        },
        "pastornino.net": {
            "ttl": 101,
            "ipid": 21588,
            "responses": 5
        },
        "medatixx.net": {
            "ttl": 101,
            "ipid": 21588,
            "responses": 4
        },
        "oticasopcao.net": {
            "ttl": 101,
            "ipid": 21588,
            "responses": 5
        },
        "logizard-plus.net": {
            "ttl": 101,
            "ipid": 21588,
            "responses": 5
        },
        "a4digitals.net": {
            "ttl": 101,
            "ipid": 21588,
            "responses": 4
        },
        "bernardclacens.net": {
            "ttl": 101,
            "ipid": 21588,
            "responses": 2
        },
        "andreassauva.net": {
            "ttl": 101,
            "ipid": 21588,
            "responses": 4
        },
        "hsbcchinalife.net": {
            "ttl": 101,
            "ipid": 21588,
            "responses": 3
        },
        "team-europe.net": {
            "ttl": 101,
            "ipid": 21588,
            "responses": 5
        },
        "joshweiss.net": {
            "ttl": 101,
            "ipid": 21588,
            "responses": 4
        },
        "neonfinger.net": {
            "ttl": 101,
            "ipid": 21588,
            "responses": 1
        },
        "theairlinegame.net": {
            "ttl": 101,
            "ipid": 21588,
            "responses": 4
        },
        "privatecopy.net": {
            "ttl": 101,
            "ipid": 21588,
            "responses": 5
        },
        "oneoakcap.net": {
            "ttl": 101,
            "ipid": 21588,
            "responses": 3
        },
        "it-nomad.net": {
            "ttl": 101,
            "ipid": 21588,
            "responses": 2
        },
        "wizardtravel.net": {
            "ttl": 101,
            "ipid": 21588,
            "responses": 2
        },
        "thejuicer.net": {
            "ttl": 101,
            "ipid": 21588,
            "responses": 4
        },
        "anacris.net": {
            "ttl": 101,
            "ipid": 21588,
            "responses": 3
        },
        "oreillyinpractice.net": {
            "ttl": 101,
            "ipid": 21588,
            "responses": 4
        },
        "kornelimuenster.net": {
            "ttl": 101,
            "ipid": 21588,
            "responses": 5
        },
        "autruetec.net": {
            "ttl": 101,
            "ipid": 21588,
            "responses": 4
        },
        "tastil.net": {
            "ttl": 101,
            "ipid": 21588,
            "responses": 2
        },
        "marcasdemadrid.net": {
            "ttl": 101,
            "ipid": 21588,
            "responses": 3
        },
        "alarmserwis.net": {
            "ttl": 101,
            "ipid": 21588,
            "responses": 2
        },
        "emvc.net": {
            "ttl": 101,
            "ipid": 21588,
            "responses": 2
        },
        "clsenglish.net": {
            "ttl": 101,
            "ipid": 21588,
            "responses": 1
        },
        "teammedics.net": {
            "ttl": 101,
            "ipid": 21588,
            "responses": 4
        },
        "brandshiftbook.net": {
            "ttl": 101,
            "ipid": 21588,
            "responses": 2
        },
        "ichabod1799.net": {
            "ttl": 101,
            "ipid": 21588,
            "responses": 4
        },
        "cocnn.net": {
            "ttl": 101,
            "ipid": 21588,
            "responses": 3
        },
        "blockmanagement.net": {
            "ttl": 101,
            "ipid": 21588,
            "responses": 3
        },
        "border-bargains.net": {
            "ttl": 101,
            "ipid": 21588,
            "responses": 2
        },
        "canalefarms.net": {
            "ttl": 101,
            "ipid": 21588,
            "responses": 4
        },
        "qmtu.net": {
            "ttl": 101,
            "ipid": 21588,
            "responses": 5
        },
        "stocking-passion.net": {
            "ttl": 101,
            "ipid": 21588,
            "responses": 1
        },
        "sxxhj.net": {
            "ttl": 101,
            "ipid": 21588,
            "responses": 2
        },
        "ricohstore.net": {
            "ttl": 101,
            "ipid": 21588,
            "responses": 2
        },
        "johnnyking.net": {
            "ttl": 101,
            "ipid": 21588,
            "responses": 1
        },
        "propeotech.net": {
            "ttl": 101,
            "ipid": 21588,
            "responses": 2
        },
        "vincentlord.net": {
            "ttl": 101,
            "ipid": 21588,
            "responses": 2
        },
        "variegatestainsealer.net": {
            "ttl": 101,
            "ipid": 21588,
            "responses": 3
        },
        "laobai.net": {
            "ttl": 101,
            "ipid": 21588,
            "responses": 1
        },
        "perlereshop.net": {
            "ttl": 101,
            "ipid": 21588,
            "responses": 2
        },
        "kylecollective.net": {
            "ttl": 101,
            "ipid": 21588,
            "responses": 2
        }
    }
}