{
    "meta": {
        "tried": 999,
        "allowed": 910,
        "blocked": 89,
        "errors": 0
    },
    "domains": {
        "02290.info": {
            "ttl": 83,
            "ipid": 57717,
            "responses": 2
        },
        "02298.info": {
            "ttl": 101,
            "ipid": 21588,
            "responses": 5
        },
        "022bhhyl.info": {
            "ttl": 101,
            "ipid": 21588,
            "responses": 5
        },
        "022ki.info": {
            "ttl": 101,
            "ipid": 21588,
            "responses": 4
        },
        "022m215.info": {
            "ttl": 101,
            "ipid": 21588,
            "responses": 8
        },
        "02311.info": {
            "ttl": 101,
            "ipid": 21588,
            "responses": 5
        },
        "02345.info": {
            "ttl": 101,
            "ipid": 21588,
            "responses": 5
        },
        "02348.info": {
            "ttl": 101,
            "ipid": 21588,
            "responses": 3
        },
        "02355.info": {
            "ttl": 101,
            "ipid": 21588,
            "responses": 7
        },
        "02361.info": {
            "ttl": 101,
            "ipid": 21588,
            "responses": 2
        },
        "02368.info": {
            "ttl": 101,
            "ipid": 21588,
            "responses": 4
        },
        "0236884.info": {
            "ttl": 101,
            "ipid": 21588,
            "responses": 5
        },
        "0237.info": {
            "ttl": 101,
            "ipid": 21588,
            "responses": 4
        },
        "02380.info": {
            "ttl": 101,
            "ipid": 21588,
            "responses": 6
        },
        "02381.info": {
            "ttl": 101,
            "ipid": 21588,
            "responses": 4
        },
        "02389.info": {
            "ttl": 101,
            "ipid": 21588,
            "responses": 2
        },
        "02394.info": {
            "ttl": 101,
            "ipid": 21588,
            "responses": 6
        },
        "02399.info": {
            "ttl": 101,
            "ipid": 21588,
            "responses": 6
        },
        "023d22450dd78245015ab2ad770d5a2c.info": {
            "ttl": 101,
            "ipid": 21588,
            "responses": 2
        },
        "023yl.info": {
            "ttl": 101,
            "ipid": 21588,
            "responses": 4
        },
        "02409.info": {
            "ttl": 101,
            "ipid": 21588,
            "responses": 4
        },
        "02417.info": {
            "ttl": 101,
            "ipid": 21588,
            "responses": 2
        },
        "024200.info": {
            "ttl": 101,
            "ipid": 21588,
            "responses": 6
        },
        "02453.info": {
            "ttl": 101,
            "ipid": 21588,
            "responses": 9
        },
        "02454.info": {
            "ttl": 101,
            "ipid": 21588,
            "responses": 6
        },
        "02463.info": {
            "ttl": 101,
            "ipid": 21588,
            "responses": 2
        },
        "02484.info": {
            "ttl": 101,
            "ipid": 21588,
            "responses": 3
        },
        "02485.info": {
            "ttl": 45,
            "ipid": 3542,
            "responses": 2
        },
        "02491.info": {
            "ttl": 101,
            "ipid": 21588,
            "responses": 3
        },
        "024h695.info": {
            "ttl": 101,
            "ipid": 21588,
            "responses": 2
        },
        "024i148.info": {
            "ttl": 101,
            "ipid": 21588,
            "responses": 5
        },
        "024j062.info": {
            "ttl": 101,
            "ipid": 21588,
            "responses": 2
        },
        "024o675.info": {
            "ttl": 101,
            "ipid": 21588,
            "responses": 9
        },
        "024o800.info": {
            "ttl": 98,
            "ipid": 23343,
            "responses": 2
        },
        "024rot.info": {
            "ttl": 101,
            "ipid": 21588,
            "responses": 8
        },
        "024slm.info": {
            "ttl": 101,
            "ipid": 21588,
            "responses": 3
        },
        "025250.info": {
            "ttl": 101,
            "ipid": 21588,
            "responses": 4
        },
        "0252505.info": {
            "ttl": 84,
            "ipid": 57721,
            "responses": 2
        },
        "02527.info": {
            "ttl": 101,
            "ipid": 21588,
            "responses": 5
        },
        "025350.info": {
            "ttl": 59,
            "ipid": 28208,
            "responses": 2
        },
        "0258.info": {
            "ttl": 101,
            "ipid": 21588,
            "responses": 3
        },
        "02580.info": {
            "ttl": 101,
            "ipid": 21588,
            "responses": 1
        },
        "02589.info": {
            "ttl": 101,
            "ipid": 21588,
            "responses": 3
        },
        "025cdc6ca7345ca89fe0250e49afb703.info": {
            "ttl": 95,
            "ipid": 10537,
            "responses": 2
        },
        "02607.info": {
            "ttl": 101,
            "ipid": 21588,
            "responses": 6
        },
        "02611.info": {
            "ttl": 101,
            "ipid": 21588,
            "responses": 5
        },
        "02632.info": {
            "ttl": 101,
            "ipid": 21588,
            "responses": 7
        },
        "02637.info": {
            "ttl": 101,
            "ipid": 21588,
            "responses": 6
        },
        "0266.info": {
            "ttl": 101,
            "ipid": 21588,
            "responses": 8
        },
        "02666.info": {
            "ttl": 101,
            "ipid": 21588,
            "responses": 4
        },
        "02685.info": {
            "ttl": 101,
            "ipid": 21588,
            "responses": 4
        },
        "02686.info": {
            "ttl": 101,
            "ipid": 21588,
            "responses": 4
        },
        "026m4.info": {
            "ttl": 97,
            "ipid": 22125,
            "responses": 2
        },
        "02746.info": {
            "ttl": 101,
            "ipid": 21588,
            "responses": 3
        },
        "02765.info": {
            "ttl": 101,
            "ipid": 21588,
            "responses": 4
        },
        "02768.info": {
            "ttl": 101,
            "ipid": 21588,
            "responses": 8
        },
        "0277.info": {
            "ttl": 101,
            "ipid": 21588,
            "responses": 2
        },
        "02772.info": {
            "ttl": 101,
            "ipid": 21588,
            "responses": 2
        },
        "02774.info": {
            "ttl": 101,
            "ipid": 21588,
            "responses": 4
        },
        "027swx.info": {
            "ttl": 101,
            "ipid": 21588,
            "responses": 3
        },
        "02802.info": {
            "ttl": 101,
            "ipid": 21588,
            "responses": 5
        },
        "028100.info": {
            "ttl": 101,
            "ipid": 21588,
            "responses": 10
        },
        "02812.info": {
            "ttl": 101,
            "ipid": 21588,
            "responses": 3
        },
        "02822.info": {
            "ttl": 101,
            "ipid": 21588,
            "responses": 1
        },
        "02844.info": {
            "ttl": 101,
            "ipid": 21588,
            "responses": 6
        },
        "02847.info": {
            "ttl": 101,
            "ipid": 21588,
            "responses": 5
        },
        "0285.info": {
            "ttl": 101,
            "ipid": 21588,
            "responses": 1
        },
        "02856.info": {
            "ttl": 101,
            "ipid": 21588,
            "responses": 5
        },
        "02860.info": {
            "ttl": 101,
            "ipid": 21588,
            "responses": 7
        },
        "028aced73addee4f81e984db07321aae.info": {
            "ttl": 101,
            "ipid": 21588,
            "responses": 8
        },
        "028c97f6f1651f141d188aec164f7caa.info": {
            "ttl": 57,
            "ipid": 25236,
            "responses": 2
        },
        "028ep.info": {
            "ttl": 101,
            "ipid": 21588,
            "responses": 4
        },
        "02900.info": {
            "ttl": 101,
            "ipid": 21588,
            "responses": 4
        },
        "02901.info": {
            "ttl": 101,
            "ipid": 21588,
            "responses": 3
        },
        "0291.info": {
            "ttl": 101,
            "ipid": 21588,
            "responses": 7
        },
        "02912.info": {
            "ttl": 101,
            "ipid": 21588,
            "responses": 4
        },
        "02922.info": {
            "ttl": 97,
            "ipid": 18948,
            "responses": 2
        },
        "02923.info": {
            "ttl": 101,
            "ipid": 21588,
            "responses": 2
        },
        "02924.info": {
            "ttl": 101,
            "ipid": 21588,
            "responses": 3
        },
        "02925.info": {
            "ttl": 101,
            "ipid": 21588,
            "responses": 2
        },
        "029276.info": {
            "ttl": 101,
            "ipid": 21588,
            "responses": 4
        },
        "02928.info": {
            "ttl": 101,
            "ipid": 21588,
            "responses": 1
        },
        "02931362.info": {
            "ttl": 101,
            "ipid": 21588,
            "responses": 7
        },
        "02933.info": {
            "ttl": 101,
            "ipid": 21588,
            "responses": 5
        },
        "02934.info": {
            "ttl": 101,
            "ipid": 21588,
            "responses": 6
        },
        "02947.info": {
            "ttl": 101,
            "ipid": 21588,
            "responses": 3
        },
        "02950.info": {
            "ttl": 101,
            "ipid": 21588,
            "responses": 2
        },
        "02988.info": {
            "ttl": 101,
            "ipid": 21588,
            "responses": 3
        },
        "02993.info": {
            "ttl": 101,
            "ipid": 21588,
            "responses": 4
        }
    }
}